{
  "London": 55,
  "Oxford": 50,
  "Cambridge": 48,
  "Brighton": 45,
  "Bristol": 42,
  "Bath": 41,
  "Reading": 40,
  "Manchester": 40,
  "Leeds": 45,
  "Birmingham": 38,
  "Nottingham": 35,
  "Sheffield": 34,
  "Liverpool": 36,
  "Newcastle": 32,
  "York": 37,
  "Durham": 39,
  "Coventry": 34,
  "Leicester": 35,
  "Derby": 32,
  "Lincoln": 30,
  "Hull": 30,
  "Huddersfield": 30,
  "Bradford": 29,
  "Middlesbrough": 27,
  "Sunderland": 28,
  "Norwich": 33,
  "Exeter": 38,
  "Plymouth": 34,
  "Portsmouth": 37,
  "Southampton": 38,
  "Bournemouth": 39,
  "Poole": 39,
  "Canterbury": 36,
  "Colchester": 34,
  "Luton": 33,
  "Hatfield": 34,
  "Bedford": 32,
  "Milton Keynes": 34,
  "Northampton": 31,
  "Wolverhampton": 31,
  "Stoke-on-Trent": 30,
  "Keele": 30,
  "Lancaster": 32,
  "Preston": 31,
  "Blackpool": 29,
  "Chester": 33,
  "Salford": 38,
  "Bolton": 31,
  "Warrington": 32,
  "Crewe": 30,
  "Bangor": 30,
  "Cardiff": 38,
  "Swansea": 34,
  "Newport": 32,
  "Wrexham": 30,
  "Aberystwyth": 29,
  "Edinburgh": 42,
  "Glasgow": 40,
  "Stirling": 32,
  "Dundee": 31,
  "Aberdeen": 33,
  "Perth": 30,
  "Inverness": 29,
  "Paisley": 32,
  "Falkirk": 30,
  "Belfast": 34,
  "Derry": 30,
  "Coleraine": 29
}
